mkdocs_github_contributors_plugin/__init__.py
mkdocs_github_contributors_plugin/plugin.py
mkdocs_github_contributors_plugin-0.1.6.dist-info/LICENSE
mkdocs_github_contributors_plugin-0.1.6.dist-info/METADATA
mkdocs_github_contributors_plugin-0.1.6.dist-info/WHEEL
mkdocs_github_contributors_plugin-0.1.6.dist-info/entry_points.txt
mkdocs_github_contributors_plugin-0.1.6.dist-info/top_level.txt
mkdocs_github_contributors_plugin-0.1.6.dist-info/RECORD
